simple_ops/__init__.py
simple_ops/operator.py
simple_operator-1.0.dist-info/METADATA
simple_operator-1.0.dist-info/WHEEL
simple_operator-1.0.dist-info/top_level.txt
simple_operator-1.0.dist-info/RECORD
