Metadata-Version: 2.1
Name: simple-operator
Version: 1.0
Summary: Simple operations
Home-page: https://github.com/Ji-Min-Lee/simple_ops
Author: Jimin Lee
Author-email: ljm94318@gmail.com
License: UNKNOWN
Keywords: operator
Platform: UNKNOWN
Classifier: Programming Language :: Python :: 3
Classifier: Programming Language :: Python :: 3.2
Classifier: Programming Language :: Python :: 3.3
Classifier: Programming Language :: Python :: 3.4
Classifier: Programming Language :: Python :: 3.5
Classifier: Programming Language :: Python :: 3.6
Classifier: Programming Language :: Python :: 3.7
Requires-Python: >=3
